{
    "i-0a2db1383f8b9dcd3": {
        "Init": "2019-09-26 05:43:37.896659"
    },
    "i-034d34504bdb58321": {
        "Init": "2019-09-27 20:53:14.124237"
    },
    "i-018d1afae0c76ec6e": {
        "Init": "2019-09-27 23:31:01.937839"
    },
    "i-0657f2fcd38cd7713": {
        "Init": "2019-09-28 01:10:05.961325"
    },
    "i-09a6c3bc40f0633bb": {
        "Init": "2019-09-28 05:36:21.085064"
    },
    "i-098f28b6717a24f52": {
        "Init": "2019-09-29 15:24:23.578638"
    },
    "i-0a8b341f54e425f7d": {
        "Token": "ledgerformat",
        "Init": "2019-09-30 15:33:52.424379"
    },
    "i-01704faf72a5fa5b9": {
        "Token": "ledgerformat",
        "Init": "2019-10-02 17:23:36.550947"
    },
    "i-047528faf646a344d": {
        "Token": "guitest1",
        "Init": "2019-10-10 13:53:50.438664"
    },
    "i-01811257fb79f0b54": {
        "Token": "guitest2",
        "Init": "2019-10-10 13:56:51.129483"
    }
}